pipurge.py
setup.py
pipurge.egg-info/PKG-INFO
pipurge.egg-info/SOURCES.txt
pipurge.egg-info/dependency_links.txt
pipurge.egg-info/entry_points.txt
pipurge.egg-info/requires.txt
pipurge.egg-info/top_level.txt