Metadata-Version: 1.1
Name: pipurge
Version: 0.2.1
Summary: Tool for quickly uninstalling python packages.
Home-page: http://github.com/jpatrickdill/pipurge
Author: Patrick Dill
Author-email: jamespatrickdill@gmail.com
License: MIT
Download-URL: http://github.com/reshanie/pipurge/archive/master.tar.gz
Platform: any
Classifier: Development Status :: 3 - Alpha
Classifier: Programming Language :: Python
Classifier: Programming Language :: Python :: 3
Classifier: Programming Language :: Python :: 3.0
Classifier: Programming Language :: Python :: 3.1
Classifier: Programming Language :: Python :: 3.2
Classifier: Programming Language :: Python :: 3.3
Classifier: Programming Language :: Python :: 3.4
Classifier: Programming Language :: Python :: 3.5
Classifier: Programming Language :: Python :: 3.6
Classifier: Intended Audience :: Developers
Classifier: Intended Audience :: System Administrators
Classifier: License :: OSI Approved :: MIT License
Classifier: Operating System :: OS Independent
Classifier: Topic :: System :: Systems Administration
